setup.py
gbcal/__init__.py
gbcal/config.py
gbcal/gbcal.py
gbcal/main.py
gbcal.egg-info/PKG-INFO
gbcal.egg-info/SOURCES.txt
gbcal.egg-info/dependency_links.txt
gbcal.egg-info/entry_points.txt
gbcal.egg-info/requires.txt
gbcal.egg-info/top_level.txt