Metadata-Version: 1.0
Name: gbcal
Version: 1.0
Summary: cli tool to manage google birthday calendar
Home-page: https://github.com/danielkraic/gbcal
Author: Daniel Kraic
Author-email: danielkraic@gmail.com
License: MIT
Platform: UNKNOWN
